README.md
setup.py
tap_x_y/__init__.py
tap_x_y/catalog.py
tap_x_y/client.py
tap_x_y/streams.py
tap_x_y/transform.py
tap_x_y.egg-info/PKG-INFO
tap_x_y.egg-info/SOURCES.txt
tap_x_y.egg-info/dependency_links.txt
tap_x_y.egg-info/entry_points.txt
tap_x_y.egg-info/requires.txt
tap_x_y.egg-info/top_level.txt
tap_x_y/schemas/customer.json
tap_x_y/schemas/inventory.json
tap_x_y/schemas/inventory_movement.json
tap_x_y/schemas/invoice.json
tap_x_y/schemas/item.json
tap_x_y/schemas/sales_order_line.json
tap_x_y/schemas/stock_transfer.json